README.rst
setup.py
mh_z19b/__index__.py
mh_z19b/async.py
mh_z19b/common.py
mh_z19b/sync.py
pymh_z19b_serial.egg-info/PKG-INFO
pymh_z19b_serial.egg-info/SOURCES.txt
pymh_z19b_serial.egg-info/dependency_links.txt
pymh_z19b_serial.egg-info/requires.txt
pymh_z19b_serial.egg-info/top_level.txt
test/test_communication.py